mseep_voice_status_report_mcp_server-0.1.4.dist-info/licenses/LICENSE
voice_status_report_mcp_server/__init__.py
voice_status_report_mcp_server/py.typed
voice_status_report_mcp_server/server.py
mseep_voice_status_report_mcp_server-0.1.4.dist-info/METADATA
mseep_voice_status_report_mcp_server-0.1.4.dist-info/WHEEL
mseep_voice_status_report_mcp_server-0.1.4.dist-info/entry_points.txt
mseep_voice_status_report_mcp_server-0.1.4.dist-info/top_level.txt
mseep_voice_status_report_mcp_server-0.1.4.dist-info/RECORD
